quaker/__init__.py
quaker/__main__.py
quaker_lib/__init__.py
quaker_lib/application.py
quaker_lib/html5writer.py
quaker_lib/index.py
quaker_lib/main.py
quaker_lib/page.py
quaker_lib/theme.py
quaker_lib/util.py
quaker_lib/directives/__init__.py
quaker_lib/directives/custom.py
quaker_lib/directives/metadata.py
quaker_lib/directives/sphinx.py
quaker_lib/quickstart/conf.py
quaker_lib/quickstart/index.rst
quaker_lib/quickstart/page.rst
quaker_lib/static/js/bookmark.js
quaker_lib/static/js/cookies.js
quaker_lib/static/js/keylistener.js
quaker_lib/static/js/script.js
quaker_lib/static/js/search.js
quaker_lib/static/quaker_theme/template.txt
quaker_lib/static/quaker_theme/theme.conf
quaker_lib/static/quaker_theme/static/css/all.min.css
quaker_lib/static/quaker_theme/static/css/bulma.min-classy.css
quaker_lib/static/quaker_theme/static/css/bulma.min-dark.css
quaker_lib/static/quaker_theme/static/css/bulma.min-jet.css
quaker_lib/static/quaker_theme/static/css/bulma.min-night.css
quaker_lib/static/quaker_theme/static/css/bulma.min-red.css
quaker_lib/static/quaker_theme/static/css/bulma.min.css
quaker_lib/static/quaker_theme/static/css/content.css
quaker_lib/static/quaker_theme/static/css/font-awesome.min.css
quaker_lib/static/quaker_theme/static/css/fontawesome.min.css
quaker_lib/static/quaker_theme/static/css/friendly.css
quaker_lib/static/quaker_theme/static/css/main.css
quaker_lib/static/quaker_theme/static/css/math.css
quaker_lib/static/quaker_theme/static/css/v4-shims.min.css
quaker_lib/static/quaker_theme/static/webfonts/fa-brands-400.eot
quaker_lib/static/quaker_theme/static/webfonts/fa-brands-400.svg
quaker_lib/static/quaker_theme/static/webfonts/fa-brands-400.ttf
quaker_lib/static/quaker_theme/static/webfonts/fa-brands-400.woff
quaker_lib/static/quaker_theme/static/webfonts/fa-brands-400.woff2
quaker_lib/static/quaker_theme/static/webfonts/fa-regular-400.eot
quaker_lib/static/quaker_theme/static/webfonts/fa-regular-400.svg
quaker-1.0.1.dist-info/LICENSE
quaker-1.0.1.dist-info/METADATA
quaker-1.0.1.dist-info/WHEEL
quaker-1.0.1.dist-info/entry_points.txt
quaker-1.0.1.dist-info/top_level.txt
quaker-1.0.1.dist-info/RECORD
