Metadata-Version: 2.1
Name: quaker
Version: 1.0.1
Summary: Static Documentation Generator
Home-page: https://www.quakerdocs.nl/
License: UNKNOWN
Platform: UNKNOWN
Classifier: Programming Language :: Python :: 3
Classifier: License :: OSI Approved :: MIT License
Classifier: Operating System :: OS Independent
Requires-Python: >=3.8
License-File: LICENSE
Requires-Dist: Pygments (==2.9.0)
Requires-Dist: docutils (==0.17.1)
Requires-Dist: Jinja2 (==2.10.3)
